uc_micro/__init__.py
uc_micro/categories/__init__.py
uc_micro/categories/Cc/__init__.py
uc_micro/categories/Cc/regex.py
uc_micro/categories/Cf/__init__.py
uc_micro/categories/Cf/regex.py
uc_micro/categories/P/__init__.py
uc_micro/categories/P/regex.py
uc_micro/categories/Z/__init__.py
uc_micro/categories/Z/regex.py
uc_micro/properties/__init__.py
uc_micro/properties/Any/__init__.py
uc_micro/properties/Any/regex.py
uc_micro_py-1.0.2.dist-info/LICENSE
uc_micro_py-1.0.2.dist-info/METADATA
uc_micro_py-1.0.2.dist-info/WHEEL
uc_micro_py-1.0.2.dist-info/top_level.txt
uc_micro_py-1.0.2.dist-info/RECORD
