Metadata-Version: 2.1
Name: uc-micro-py
Version: 1.0.2
Summary: Micro subset of unicode data files for linkify-it-py projects.
Author: tsutsu3
License: MIT
Project-URL: Homepage, https://github.com/tsutsu3/uc.micro-py
Keywords: unicode
Classifier: Development Status :: 5 - Production/Stable
Classifier: Programming Language :: Python :: 3
Classifier: Programming Language :: Python :: 3.7
Classifier: Programming Language :: Python :: 3.8
Classifier: Programming Language :: Python :: 3.9
Classifier: Programming Language :: Python :: 3.10
Classifier: Programming Language :: Python :: 3.11
Classifier: License :: OSI Approved :: MIT License
Classifier: Operating System :: OS Independent
Classifier: Intended Audience :: Developers
Classifier: Topic :: Software Development :: Libraries :: Python Modules
Requires-Python: >=3.7
Provides-Extra: test
License-File: LICENSE
